{
	"name": "Incremetal_Load_Extract",
	"properties": {
		"annotations": [],
		"runtimeState": "Stopped",
		"pipelines": [
			{
				"pipelineReference": {
					"referenceName": "EPSDL_Master_Pipeline_incremental",
					"type": "PipelineReference"
				}
			}
		],
		"type": "ScheduleTrigger",
		"typeProperties": {
			"recurrence": {
				"frequency": "Day",
				"interval": 1,
				"startTime": "2020-10-13T11:25:00.000Z",
				"timeZone": "UTC",
				"schedule": {
					"minutes": [
						30
					],
					"hours": [
						21
					]
				}
			}
		}
	}
}